{
  "type": "minecraft:crafting_shaped",
  "key": {
    "A": {
      "item": "draconicevolution:item_draconium_damage"
    },
    "B": {
      "item": "draconicevolution:draconium_core"
    },
    "I": {
      "tag": "forge:ingots/draconium"
    },
    "P": {
      "type": "forge:nbt",
      "count": 1,
      "item": "minecraft:potion",
      "nbt": "{Potion:\"minecraft:strong_strength\"}"
    }
  },
  "pattern": [
    "IPI",
    "ABA",
    "IPI"
  ],
  "result": {
    "item": "draconicevolution:item_wyvern_damage"
  }
}